{
    "title": "Back to Top",
    "tag": "ilw-back-to-top",
	"github": "https://github.com/web-illinois/ilw-back-to-top",
    "type": "web component",
    "element-name": "ilw-back-to-top",
	"description": "The Illinois component back-to-top allows you to provide a simple way to skip either to the top of a page or to a designated point in the page (such as the page content area). You can choose alternate Illinois brand colors and adjust the position of the arrow.",
	"version": "1.0.0-alpha",
	"date": "6/7/2024",
	"css": "https://dev.toolkit.illinois.edu/ilw-back-to-top/1.0.0-alpha/ilw-back-to-top.css",
	"js": "https://dev.toolkit.illinois.edu/ilw-back-to-top/1.0.0-alpha/ilw-back-to-top.js",
	"production": false,
    "notes": "",
	"parent-style": "",
	"attributes-fixed": [],
	"attributes-text": [
		{
			"depreciated": false,
			"name": "target",
			"description" : "The ID of the element which represents the top of the page. If provided, the page will scroll to this element.",
			"value": ""
		},
		{
			"depreciated": false,
			"name": "alt",
			"description" : "The accessible text label of the button, defaults to 'Back to top'",
			"value": ""
		}
	],
	"attributes" : [],
	"classes-fixed": [],
	"classes": [],
	"css-variables" : [
		{
			"name": "--ilw-back-to-top--color",
			"description" : "Hex color of the arrow and border",
			"depreciated": false
		},
		{
			"name": "--ilw-back-to-top--background",
			"description" : "Background hex color",
			"depreciated": false
		},
		{
			"name": "--ilw-back-to-top--bottom",
			"description" : "Position in pixels from the bottom of the screen",
			"depreciated": false
		},
		{
			"name": "--ilw-back-to-top--right",
			"description" : "Position in pixels from the right of the screen",
			"depreciated": false
		}
	]
}